{
    "$schema": "https://schema.management.azure.com/schemas/2015-01-01/deploymentTemplate.json#",
    "contentVersion": "1.0.0.0",
    "parameters": {
        "webappname": {
            "defaultValue": "mvc-arm-30210",
            "type": "String"
        },
        "appservicename": {
            "defaultValue": "arm-30210",
            "type": "String"
        }
    },
    "variables": {
    },
    "resources": [
        {
            "type": "Microsoft.Web/serverfarms",
            "apiVersion": "2018-02-01",
            "name": "[parameters('appservicename')]",
            "location": "West Europe",
            "sku": {
                "name": "F1",
                "tier": "Free",
                "size": "F1",
                "family": "F",
                "capacity": 0
            },
            "kind": "app",
            "properties": {
                "perSiteScaling": false,
                "maximumElasticWorkerCount": 1,
                "isSpot": false,
                "reserved": false,
                "isXenon": false,
                "hyperV": false,
                "targetWorkerCount": 0,
                "targetWorkerSizeId": 0
            }
        },
        {
            "type": "Microsoft.Web/sites",
            "apiVersion": "2018-11-01",
            "name": "[parameters('webappname')]",
            "location": "West Europe",
            "dependsOn": [
                "[resourceId('Microsoft.Web/serverfarms', parameters('appservicename'))]"
            ],
            "kind": "app",
            "properties": {
                "enabled": true,
                "hostNameSslStates": [
                    {
                        "name": "[concat(parameters('webappname'), '.azurewebsites.net')]",
                        "sslState": "Disabled",
                        "hostType": "Standard"
                    },
                    {
                        "name": "[concat(parameters('webappname'), '.scm.azurewebsites.net')]",
                        "sslState": "Disabled",
                        "hostType": "Repository"
                    }
                ],
                "serverFarmId": "[resourceId('Microsoft.Web/serverfarms', parameters('appservicename'))]",
                "reserved": false,
                "isXenon": false,
                "hyperV": false,
                "siteConfig": {
                },
                "scmSiteAlsoStopped": false,
                "clientAffinityEnabled": true,
                "clientCertEnabled": false,
                "hostNamesDisabled": false,
                "containerSize": 0,
                "dailyMemoryTimeQuota": 0,
                "httpsOnly": false,
                "redundancyMode": "None"
            }
        },
        {
            "type": "Microsoft.Web/sites/config",
            "apiVersion": "2018-11-01",
            "name": "[concat(parameters('webappname'), '/web')]",
            "location": "West Europe",
            "dependsOn": [
                "[resourceId('Microsoft.Web/sites', parameters('webappname'))]"
            ],
            "properties": {
                "numberOfWorkers": 1,
                "defaultDocuments": [
                    "Default.htm",
                    "Default.html",
                    "Default.asp",
                    "index.htm",
                    "index.html",
                    "iisstart.htm",
                    "default.aspx",
                    "index.php",
                    "hostingstart.html"
                ],
                "netFrameworkVersion": "v4.0",
                "phpVersion": "5.6",
                "requestTracingEnabled": false,
                "remoteDebuggingEnabled": false,
                "httpLoggingEnabled": false,
                "logsDirectorySizeLimit": 35,
                "detailedErrorLoggingEnabled": false,
                "publishingUsername": "$mvc-arm-30210",
                "scmType": "None",
                "use32BitWorkerProcess": true,
                "webSocketsEnabled": false,
                "alwaysOn": false,
                "managedPipelineMode": "Integrated",
                "virtualApplications": [
                    {
                        "virtualPath": "/",
                        "physicalPath": "site\\wwwroot",
                        "preloadEnabled": false
                    }
                ],
                "loadBalancing": "LeastRequests",
                "experiments": {
                    "rampUpRules": [
                    ]
                },
                "autoHealEnabled": false,
                "localMySqlEnabled": false,
                "ipSecurityRestrictions": [
                    {
                        "ipAddress": "Any",
                        "action": "Allow",
                        "priority": 1,
                        "name": "Allow all",
                        "description": "Allow all access"
                    }
                ],
                "scmIpSecurityRestrictions": [
                    {
                        "ipAddress": "Any",
                        "action": "Allow",
                        "priority": 1,
                        "name": "Allow all",
                        "description": "Allow all access"
                    }
                ],
                "scmIpSecurityRestrictionsUseMain": false,
                "http20Enabled": true,
                "minTlsVersion": "1.2",
                "ftpsState": "AllAllowed",
                "reservedInstanceCount": 0
            }
        },
        {
            "type": "Microsoft.Web/sites/hostNameBindings",
            "apiVersion": "2018-11-01",
            "name": "[concat(parameters('webappname'), '/', parameters('webappname'), '.azurewebsites.net')]",
            "location": "West Europe",
            "dependsOn": [
                "[resourceId('Microsoft.Web/sites', parameters('webappname'))]"
            ],
            "properties": {
                "siteName": "mvc-arm-30210",
                "hostNameType": "Verified"
            }
        }
    ]
}